AUTHORS
LICENSE
README.md
setup.py
causal_conv1d/__init__.py
causal_conv1d/causal_conv1d_interface.py
causal_conv1d/causal_conv1d_varlen.py
causal_conv1d.egg-info/PKG-INFO
causal_conv1d.egg-info/SOURCES.txt
causal_conv1d.egg-info/dependency_links.txt
causal_conv1d.egg-info/requires.txt
causal_conv1d.egg-info/top_level.txt