Metadata-Version: 2.1
Name: causal-conv1d
Version: 1.5.0.post5
Summary: Causal depthwise conv1d in CUDA, with a PyTorch interface
Home-page: https://github.com/Dao-AILab/causal-conv1d
Author: Tri Dao
Author-email: tri@tridao.me
Classifier: Programming Language :: Python :: 3
Classifier: License :: OSI Approved :: BSD License
Classifier: Operating System :: Unix
Requires-Python: >=3.9
License-File: LICENSE
License-File: AUTHORS
